jsondate3/__init__.py
tests/__init__.py
tests/test_jsondate.py
jsondate3_aware-0.2.1.dist-info/LICENSE
jsondate3_aware-0.2.1.dist-info/METADATA
jsondate3_aware-0.2.1.dist-info/WHEEL
jsondate3_aware-0.2.1.dist-info/top_level.txt
jsondate3_aware-0.2.1.dist-info/RECORD
